nonebot_plugin_colormind/__init__.py
nonebot_plugin_colormind-0.1.0.dist-info/LICENSE
nonebot_plugin_colormind-0.1.0.dist-info/WHEEL
nonebot_plugin_colormind-0.1.0.dist-info/METADATA
nonebot_plugin_colormind-0.1.0.dist-info/RECORD
