Metadata-Version: 2.1
Name: nonebot-plugin-colormind
Version: 0.1.0
Summary: A plugin for nonebot2. Query Bilibili user information（一个Nonebot2的插件，b站用户信息查询插件【粉丝、舰团信息；直播收益数据；直播观看信息；关键词搜昵称、UID等】）
Home-page: https://github.com/Ikaros-521/nonebot_plugin_colormind
License: MIT
Author: Ikaros
Author-email: 327209194@qq.com
Requires-Python: >=3.8,<4.0
Classifier: License :: OSI Approved :: MIT License
Classifier: Programming Language :: Python :: 3
Classifier: Programming Language :: Python :: 3.8
Classifier: Programming Language :: Python :: 3.9
Classifier: Programming Language :: Python :: 3.10
Classifier: Programming Language :: Python :: 3.11
Requires-Dist: aiohttp (>=3.8.3,<4.0.0)
Requires-Dist: nonebot-adapter-onebot (>=2.1.3,<3.0.0)
Requires-Dist: nonebot-plugin-htmlrender (>=0.2.0.1,<0.3.0.0)
Requires-Dist: nonebot2 (>=2.0.0b5,<3.0.0)
Project-URL: Documentation, https://github.com/Ikaros-521/nonebot_plugin_colormind/blob/master/README.md
Project-URL: Repository, https://github.com/Ikaros-521/nonebot_plugin_colormind
